ShejimoshiJingjieGof23ZhongShejimoshiJiexiFuCShixianYuanma/README.md
ShejimoshiJingjieGof23ZhongShejimoshiJiexiFuCShixianYuanma/__init__.py
ShejimoshiJingjieGof23ZhongShejimoshiJiexiFuCShixianYuanma/__main__.py
ShejimoshiJingjieGof23ZhongShejimoshiJiexiFuCShixianYuanma/file.pdf
ShejimoshiJingjieGof23ZhongShejimoshiJiexiFuCShixianYuanma/index.html
shejimoshi_jingjie_gof_23_zhong_shejimoshi_jiexi_fu_c_shixian_yuanma-2024.3.2.0.dist-info/METADATA
shejimoshi_jingjie_gof_23_zhong_shejimoshi_jiexi_fu_c_shixian_yuanma-2024.3.2.0.dist-info/WHEEL
shejimoshi_jingjie_gof_23_zhong_shejimoshi_jiexi_fu_c_shixian_yuanma-2024.3.2.0.dist-info/entry_points.txt
shejimoshi_jingjie_gof_23_zhong_shejimoshi_jiexi_fu_c_shixian_yuanma-2024.3.2.0.dist-info/top_level.txt
shejimoshi_jingjie_gof_23_zhong_shejimoshi_jiexi_fu_c_shixian_yuanma-2024.3.2.0.dist-info/RECORD
